versol/__init__.py
versol/_solution.py
versol/incompatibility.py
versol/interfaces.py
versol/iset.py
versol/iset_test.py
versol/py.typed
versol/report.py
versol/solve.py
versol/solve_test.py
versol/term.py
versol/util.py
versol-0.1.2.dist-info/LICENSE.txt
versol-0.1.2.dist-info/METADATA
versol-0.1.2.dist-info/WHEEL
versol-0.1.2.dist-info/RECORD
